LICENSE
README.md
setup.py
cerebro/__init__.py
cerebro/refactoring/__init__.py
cerebro/refactoring/meta.py
cerebro/refactoring/object.py
cerebro/refactoring/datastructs/__init__.py
cerebro/refactoring/datastructs/stack.py
cerebro/refactoring/datastructs/trees/__init__.py
cerebro/refactoring/datastructs/trees/general.py
cerebro/refactoring/designs/__init__.py
cerebro/refactoring/designs/behaviours/__init__.py
cerebro/refactoring/designs/behaviours/batchprocess.py
cerebro/refactoring/designs/behaviours/component.py
cerebro/refactoring/designs/creations/__init__.py
cerebro/refactoring/designs/creations/singleton.py
cerebro/refactoring/serializations/__init__.py
cerebro/refactoring/serializations/base.py
cerebro/refactoring/serializations/json.py
cerebro/utils/__init__.py
cerebro/utils/io/__init__.py
cerebro/utils/io/path.py
cerebro/utils/log/__init__.py
cerebro/utils/log/logging.py
cerebro_refactoring.egg-info/PKG-INFO
cerebro_refactoring.egg-info/SOURCES.txt
cerebro_refactoring.egg-info/dependency_links.txt
cerebro_refactoring.egg-info/namespace_packages.txt
cerebro_refactoring.egg-info/top_level.txt
cerebro_refactoring.egg-info/zip-safe