Metadata-Version: 2.1
Name: cerebro-refactoring
Version: 0.1.3.9.3
Summary: Provide systematic process of improving code without creating new functionality that can transform a mess into clean code and simple design.
Home-page: https://github.com/hieupth/cerebro-refactoring
Author: Hieu Pham
Author-email: hieupt.ai@gmail.com
License: MIT
Download-URL: https://github.com/hieupth/cerebro-refactoring/archive/v_01.tar.gz
Keywords: refactoring,data structures,design patterns
Platform: UNKNOWN
Classifier: Development Status :: 1 - Planning
Classifier: Intended Audience :: Developers
Classifier: Topic :: Software Development :: Build Tools
Classifier: License :: OSI Approved :: MIT License
Classifier: Programming Language :: Python :: 3
Classifier: Programming Language :: Python :: 3.5
Classifier: Programming Language :: Python :: 3.6
Classifier: Programming Language :: Python :: 3.7
Classifier: Programming Language :: Python :: 3.8
Classifier: Programming Language :: Python :: 3.9
License-File: LICENSE
